{
  "_class": "group",
  "do_objectID": "EE53F626-B129-4EA2-934D-84F17B80FC33",
  "exportOptions": {
    "_class": "exportOptions",
    "exportFormats": [
    ],
    "includedLayerIds": [
    ],
    "layerOptions": 0,
    "shouldTrim": false
  },
  "frame": {
    "_class": "rect",
    "constrainProportions": false,
    "height": 42,
    "width": 29.8666666666667,
    "x": 227.7333333333334,
    "y": 0
  },
  "hasClickThrough": false,
  "isFlippedHorizontal": false,
  "isFlippedVertical": false,
  "isLocked": false,
  "isVisible": true,
  "layerListExpandedType": 0,
  "layers": [
    {
      "class": "shapeGroup",
      "id": "AEE6C9DE-7FF7-4E3D-8DFF-7C9340827193"
    },
    {
      "class": "text",
      "id": "8C86072F-3D8E-484C-A4B2-5300D11AAE49"
    }
  ],
  "name": "n",
  "nameIsFixed": true,
  "resizingConstraint": 63,
  "resizingType": 0,
  "rotation": 0,
  "shouldBreakMaskChain": false,
  "style": {
    "_class": "style",
    "endDecorationType": 0,
    "miterLimit": 10,
    "startDecorationType": 0
  }
}